pywebmedia/__init__.py
pywebmedia-0.0.1.dist-info/LICENSE
pywebmedia-0.0.1.dist-info/METADATA
pywebmedia-0.0.1.dist-info/WHEEL
pywebmedia-0.0.1.dist-info/top_level.txt
pywebmedia-0.0.1.dist-info/RECORD
