Metadata-Version: 2.1
Name: pywebmedia
Version: 0.0.1
Summary: A Python Package to Download  Online Media Files
Home-page: https://github.com/Slime-Projects/PyWebMedia
Author: Sijey Praveen
Author-email: cjpraveen@hotmail.com
License: UNKNOWN
Project-URL: Bug Tracker, https://github.com/Slime-Projects/PyWebMedia/issues
Platform: UNKNOWN
Classifier: Programming Language :: Python :: 3
Classifier: License :: OSI Approved :: MIT License
Classifier: Operating System :: OS Independent
Requires-Python: >=3.6
